finanzb/__init__.py
finanzb/eval.py
finanzb-0.1.dist-info/METADATA
finanzb-0.1.dist-info/WHEEL
finanzb-0.1.dist-info/top_level.txt
finanzb-0.1.dist-info/RECORD
