Metadata-Version: 2.1
Name: finanzb
Version: 0.1
Summary: Paquete para realizar evaluacion financiera de proyectos
Home-page: https://github.com/msalaztor
Author: Mario Rene Salazar Torres
Author-email: mrsalazar@outlook.com
License: UNKNOWN
Platform: UNKNOWN
Classifier: Programming Language :: Python :: 3
Classifier: License :: OSI Approved :: MIT License
Classifier: Operating System :: OS Independent
Classifier: Topic :: Office/Business :: Financial
Classifier: Topic :: Office/Business :: Financial :: Investment
Requires-Python: >=3.6
Requires-Dist: numpy-financial
